LICENSE
MANIFEST.in
README.md
requirements.txt
setup.cfg
setup.py
taxonomy-viz.gif
tdtax/__init__.py
tdtax/cataclysmic.yaml
tdtax/eclipsing.yaml
tdtax/eruptive.yaml
tdtax/nonstellar.yaml
tdtax/pulsating.yaml
tdtax/rotating.yaml
tdtax/schema.json
tdtax/supernovae.yaml
tdtax/top.yaml
tdtax/util.py
tdtax/validate.py
tdtax/viz_template.html
tdtax/test/__init__.py
tdtax/test/bad.yaml
tdtax/test/test_class_yaml.py
tdtax/test/test_validate.py