Metadata-Version: 2.1
Name: tdtax
Version: 0.1.3
Summary: Taxonomy for Time-Domain Astronomy Classes
Home-page: https://github.com/profjsb/timedomain-taxonomy
Author: Josh Bloom
Author-email: joshbloom@berkeley.edu
License: BSD 3-Clause
Platform: UNKNOWN
Classifier: Development Status :: 4 - Beta
Classifier: Environment :: Console
Classifier: Intended Audience :: Science/Research
Classifier: License :: OSI Approved :: BSD License
Classifier: Operating System :: POSIX
Classifier: Programming Language :: Python :: 3.6
Classifier: Programming Language :: Python :: 3.7
Classifier: Programming Language :: Python :: 3.8
Classifier: Topic :: Internet
Classifier: Topic :: Scientific/Engineering :: Astronomy
Requires-Python: >=3.6
